foundry_db/__init__.py
foundry_db/enums/__init__.py
foundry_db/enums/id_query_types.py
foundry_db/sdk/__init__.py
foundry_db/sdk/sql_db.py
foundry_db/sdk/table_id_query_builder.py
foundry_db/tables/__init__.py
foundry_db/tables/base_table.py
foundry_db/tables/category.py
foundry_db/tables/company.py
foundry_db/tables/datapoints.py
foundry_db/tables/dates.py
foundry_db/tables/flags.py
foundry_db/tables/price_discounts.py
foundry_db/tables/product_categories.py
foundry_db/tables/products.py
foundry_db/tables/regions.py
foundry_db/tables/sales.py
foundry_db/tables/sku_table.py
foundry_db/tables/stores.py
foundry_db/tables/time_region_features.py
foundry_db/tables/time_region_features_description.py
foundry_db/tables/time_store_features.py
foundry_db/tables/time_store_features_description.py
foundry_db-0.1.30.dist-info/METADATA
foundry_db-0.1.30.dist-info/WHEEL
foundry_db-0.1.30.dist-info/top_level.txt
foundry_db-0.1.30.dist-info/RECORD
